fastcsv/__init__.py
fastcsv/_native.cp311-win_amd64.pyd
pyfastcsv-0.2.0.dist-info/licenses/LICENSE
pyfastcsv-0.2.0.dist-info/METADATA
pyfastcsv-0.2.0.dist-info/WHEEL
pyfastcsv-0.2.0.dist-info/top_level.txt
pyfastcsv-0.2.0.dist-info/RECORD
