Metadata-Version: 2.4
Name: pyfastcsv
Version: 0.2.0
Summary: High-performance CSV parsing library for Python with SIMD optimizations
Author-email: FastCSV Contributors <patsi2@yandex.ru>
License-Expression: MIT
Project-URL: Homepage, https://github.com/baksvell/FastCSV
Project-URL: Documentation, https://github.com/baksvell/FastCSV#readme
Project-URL: Repository, https://github.com/baksvell/FastCSV
Project-URL: Issues, https://github.com/baksvell/FastCSV/issues
Keywords: csv,parser,performance,simd,avx2,sse4,fast,optimized
Classifier: Development Status :: 4 - Beta
Classifier: Intended Audience :: Developers
Classifier: Programming Language :: Python :: 3
Classifier: Programming Language :: Python :: 3.10
Classifier: Programming Language :: Python :: 3.11
Classifier: Programming Language :: Python :: 3.12
Classifier: Programming Language :: C++
Classifier: Topic :: Software Development :: Libraries :: Python Modules
Classifier: Topic :: Text Processing :: Markup
Classifier: Operating System :: OS Independent
Requires-Python: >=3.10
License-File: LICENSE
Provides-Extra: dev
Requires-Dist: pytest>=7.0; extra == "dev"
Requires-Dist: pytest-benchmark>=4.0; extra == "dev"
Dynamic: license-file
